swgoh_comlink/__init__.py
swgoh_comlink/exceptions.py
swgoh_comlink/globals.py
swgoh_comlink/helpers.py
swgoh_comlink/manager.py
swgoh_comlink/models.py
swgoh_comlink/swgoh_comlink.py
swgoh_comlink/validators.py
swgoh_comlink/version.py
swgoh_comlink/StatCalc/stat_calculator.py
swgoh_comlink-1.17.0.dist-info/licenses/LICENSE
swgoh_comlink-1.17.0.dist-info/METADATA
swgoh_comlink-1.17.0.dist-info/WHEEL
swgoh_comlink-1.17.0.dist-info/top_level.txt
swgoh_comlink-1.17.0.dist-info/RECORD
