Metadata-Version: 2.4
Name: swgoh_comlink
Version: 1.17.0
Summary: Python 3 interface library for swgoh-comlink (https://github.com/swgoh-utils/swgoh-comlink)
Author-email: Mar Trepodi <martrepodi@gmail.com>
Project-URL: Homepage, https://github.com/swgoh-utils/comlink-python
Project-URL: Bug Tracker, https://github.com/swgoh-utils/comlink-python/issues
Classifier: Programming Language :: Python :: 3
Classifier: Programming Language :: Python :: 3.10
Classifier: Programming Language :: Python :: 3.11
Classifier: Programming Language :: Python :: 3.12
Classifier: License :: OSI Approved :: MIT License
Classifier: Operating System :: OS Independent
Requires-Python: >=3.10
License-File: LICENSE
Requires-Dist: hatch>=1.14.2
Requires-Dist: hatchling>=1.27.0
Requires-Dist: requests>=2.32.4
Requires-Dist: sentinels
Requires-Dist: setuptools>=75.8.1
Dynamic: license-file
